fqt/__init__.py
fqt/interpolate.py
fqt/transformer.py
fqt/utils.py
fqt-0.0.3.dev0.dist-info/METADATA
fqt-0.0.3.dev0.dist-info/WHEEL
fqt-0.0.3.dev0.dist-info/licenses/LICENSE
fqt-0.0.3.dev0.dist-info/RECORD
