Metadata-Version: 2.4
Name: fqt
Version: 0.0.3.dev0
Summary: Fast Quantile Transformer
License: BSD 3-Clause License
License-File: LICENSE
Requires-Dist: array-api-compat
Requires-Dist: scikit-learn>=1.6.2
Requires-Dist: scipy>=1.14.0
Requires-Dist: torch
Provides-Extra: dev
Requires-Dist: pytest>=6.2.4; extra == 'dev'
